.gitignore
README.rst
requirements.txt
setup.py
guix_import_debian/__init__.py
guix_import_debian/__main__.py
guix_import_debian/__version.py
guix_import_debian/base32.py
guix_import_debian/deb.py
guix_import_debian/mappings.py
guix_import_debian/query.py
guix_import_debian.egg-info/PKG-INFO
guix_import_debian.egg-info/SOURCES.txt
guix_import_debian.egg-info/dependency_links.txt
guix_import_debian.egg-info/entry_points.txt
guix_import_debian.egg-info/requires.txt
guix_import_debian.egg-info/top_level.txt