Metadata-Version: 1.1
Name: guix-import-debian
Version: 0.1
Summary: Helper for converting Debian packages into Guix package definitions
Home-page: https://gitlab.com/htgoebel/guix-import-debian
Author: Hartmut Goebel
Author-email: h.goebel@crazy-compilers.com
License: GPLv3+
Platform: UNKNOWN
Classifier: Development Status :: 3 - Alpha
Classifier: Environment :: Console
Classifier: Intended Audience :: Developers
Classifier: License :: OSI Approved :: GNU General Public License v3 or later (GPLv3+)
Classifier: Natural Language :: English
Classifier: Operating System :: POSIX :: Linux
Classifier: Programming Language :: Python
